jars/__init__.py
jars/jardata.py
jars-0.0.1.dist-info/LICENSE
jars-0.0.1.dist-info/WHEEL
jars-0.0.1.dist-info/METADATA
jars-0.0.1.dist-info/RECORD
